gradio_bettertextbox/__init__.py
gradio_bettertextbox/bettertextbox.py
gradio_bettertextbox/bettertextbox.pyi
gradio_bettertextbox/templates/component/__vite-browser-external-2447137e.js
gradio_bettertextbox/templates/component/index.js
gradio_bettertextbox/templates/component/style.css
gradio_bettertextbox/templates/component/wrapper-6f348d45-f837cf34.js
gradio_bettertextbox/templates/example/index.js
gradio_bettertextbox/templates/example/style.css
gradio_bettertextbox-0.0.3.dist-info/METADATA
gradio_bettertextbox-0.0.3.dist-info/WHEEL
gradio_bettertextbox-0.0.3.dist-info/RECORD
